{
    "_links": {
        "comments": {
            "href": "https://api.github.com/repos/runforesight/foresight-cli/issues/2/comments"
        },
        "commits": {
            "href": "https://api.github.com/repos/runforesight/foresight-cli/pulls/2/commits"
        },
        "html": {
            "href": "https://github.com/runforesight/foresight-cli/pull/2"
        },
        "issue": {
            "href": "https://api.github.com/repos/runforesight/foresight-cli/issues/2"
        },
        "review_comment": {
            "href": "https://api.github.com/repos/runforesight/foresight-cli/pulls/comments{/number}"
        },
        "review_comments": {
            "href": "https://api.github.com/repos/runforesight/foresight-cli/pulls/2/comments"
        },
        "self": {
            "href": "https://api.github.com/repos/runforesight/foresight-cli/pulls/2"
        },
        "statuses": {
            "href": "https://api.github.com/repos/runforesight/foresight-cli/statuses/0e112612b8f8d18aba7c609accbc277ac01b127b"
        }
    },
    "active_lock_reason": null,
    "additions": 164,
    "assignee": null,
    "assignees": [],
    "author_association": "CONTRIBUTOR",
    "auto_merge": null,
    "base": {
        "label": "runforesight:master",
        "ref": "master",
        "repo": {
            "allow_forking": true,
            "archive_url": "https://api.github.com/repos/runforesight/foresight-cli/{archive_format}{/ref}",
            "archived": false,
            "assignees_url": "https://api.github.com/repos/runforesight/foresight-cli/assignees{/user}",
            "blobs_url": "https://api.github.com/repos/runforesight/foresight-cli/git/blobs{/sha}",
            "branches_url": "https://api.github.com/repos/runforesight/foresight-cli/branches{/branch}",
            "clone_url": "https://github.com/runforesight/foresight-cli.git",
            "collaborators_url": "https://api.github.com/repos/runforesight/foresight-cli/collaborators{/collaborator}",
            "comments_url": "https://api.github.com/repos/runforesight/foresight-cli/comments{/number}",
            "commits_url": "https://api.github.com/repos/runforesight/foresight-cli/commits{/sha}",
            "compare_url": "https://api.github.com/repos/runforesight/foresight-cli/compare/{base}...{head}",
            "contents_url": "https://api.github.com/repos/runforesight/foresight-cli/contents/{+path}",
            "contributors_url": "https://api.github.com/repos/runforesight/foresight-cli/contributors",
            "created_at": "2021-12-22T06:18:56Z",
            "default_branch": "master",
            "deployments_url": "https://api.github.com/repos/runforesight/foresight-cli/deployments",
            "description": "Foresight CLI",
            "disabled": false,
            "downloads_url": "https://api.github.com/repos/runforesight/foresight-cli/downloads",
            "events_url": "https://api.github.com/repos/runforesight/foresight-cli/events",
            "fork": false,
            "forks": 1,
            "forks_count": 1,
            "forks_url": "https://api.github.com/repos/runforesight/foresight-cli/forks",
            "full_name": "runforesight/foresight-cli",
            "git_commits_url": "https://api.github.com/repos/runforesight/foresight-cli/git/commits{/sha}",
            "git_refs_url": "https://api.github.com/repos/runforesight/foresight-cli/git/refs{/sha}",
            "git_tags_url": "https://api.github.com/repos/runforesight/foresight-cli/git/tags{/sha}",
            "git_url": "git://github.com/runforesight/foresight-cli.git",
            "has_discussions": false,
            "has_downloads": true,
            "has_issues": true,
            "has_pages": false,
            "has_projects": false,
            "has_wiki": true,
            "homepage": "",
            "hooks_url": "https://api.github.com/repos/runforesight/foresight-cli/hooks",
            "html_url": "https://github.com/runforesight/foresight-cli",
            "id": 440754461,
            "is_template": false,
            "issue_comment_url": "https://api.github.com/repos/runforesight/foresight-cli/issues/comments{/number}",
            "issue_events_url": "https://api.github.com/repos/runforesight/foresight-cli/issues/events{/number}",
            "issues_url": "https://api.github.com/repos/runforesight/foresight-cli/issues{/number}",
            "keys_url": "https://api.github.com/repos/runforesight/foresight-cli/keys{/key_id}",
            "labels_url": "https://api.github.com/repos/runforesight/foresight-cli/labels{/name}",
            "language": "TypeScript",
            "languages_url": "https://api.github.com/repos/runforesight/foresight-cli/languages",
            "license": {
                "key": "apache-2.0",
                "name": "Apache License 2.0",
                "node_id": "MDc6TGljZW5zZTI=",
                "spdx_id": "Apache-2.0",
                "url": "https://api.github.com/licenses/apache-2.0"
            },
            "merges_url": "https://api.github.com/repos/runforesight/foresight-cli/merges",
            "milestones_url": "https://api.github.com/repos/runforesight/foresight-cli/milestones{/number}",
            "mirror_url": null,
            "name": "foresight-cli",
            "node_id": "R_kgDOGkVhHQ",
            "notifications_url": "https://api.github.com/repos/runforesight/foresight-cli/notifications{?since,all,participating}",
            "open_issues": 1,
            "open_issues_count": 1,
            "owner": {
                "avatar_url": "https://avatars.githubusercontent.com/u/103429428?v=4",
                "events_url": "https://api.github.com/users/runforesight/events{/privacy}",
                "followers_url": "https://api.github.com/users/runforesight/followers",
                "following_url": "https://api.github.com/users/runforesight/following{/other_user}",
                "gists_url": "https://api.github.com/users/runforesight/gists{/gist_id}",
                "gravatar_id": "",
                "html_url": "https://github.com/runforesight",
                "id": 103429428,
                "login": "runforesight",
                "node_id": "O_kgDOBio1NA",
                "organizations_url": "https://api.github.com/users/runforesight/orgs",
                "received_events_url": "https://api.github.com/users/runforesight/received_events",
                "repos_url": "https://api.github.com/users/runforesight/repos",
                "site_admin": false,
                "starred_url": "https://api.github.com/users/runforesight/starred{/owner}{/repo}",
                "subscriptions_url": "https://api.github.com/users/runforesight/subscriptions",
                "type": "Organization",
                "url": "https://api.github.com/users/runforesight"
            },
            "private": false,
            "pulls_url": "https://api.github.com/repos/runforesight/foresight-cli/pulls{/number}",
            "pushed_at": "2023-02-20T12:51:45Z",
            "releases_url": "https://api.github.com/repos/runforesight/foresight-cli/releases{/id}",
            "size": 1069,
            "ssh_url": "git@github.com:runforesight/foresight-cli.git",
            "stargazers_count": 3,
            "stargazers_url": "https://api.github.com/repos/runforesight/foresight-cli/stargazers",
            "statuses_url": "https://api.github.com/repos/runforesight/foresight-cli/statuses/{sha}",
            "subscribers_url": "https://api.github.com/repos/runforesight/foresight-cli/subscribers",
            "subscription_url": "https://api.github.com/repos/runforesight/foresight-cli/subscription",
            "svn_url": "https://github.com/runforesight/foresight-cli",
            "tags_url": "https://api.github.com/repos/runforesight/foresight-cli/tags",
            "teams_url": "https://api.github.com/repos/runforesight/foresight-cli/teams",
            "topics": [],
            "trees_url": "https://api.github.com/repos/runforesight/foresight-cli/git/trees{/sha}",
            "updated_at": "2023-01-31T19:23:30Z",
            "url": "https://api.github.com/repos/runforesight/foresight-cli",
            "visibility": "public",
            "watchers": 3,
            "watchers_count": 3,
            "web_commit_signoff_required": false
        },
        "sha": "abf08c03b54a829c41ecf2b6f0e17e527e81f951",
        "user": {
            "avatar_url": "https://avatars.githubusercontent.com/u/103429428?v=4",
            "events_url": "https://api.github.com/users/runforesight/events{/privacy}",
            "followers_url": "https://api.github.com/users/runforesight/followers",
            "following_url": "https://api.github.com/users/runforesight/following{/other_user}",
            "gists_url": "https://api.github.com/users/runforesight/gists{/gist_id}",
            "gravatar_id": "",
            "html_url": "https://github.com/runforesight",
            "id": 103429428,
            "login": "runforesight",
            "node_id": "O_kgDOBio1NA",
            "organizations_url": "https://api.github.com/users/runforesight/orgs",
            "received_events_url": "https://api.github.com/users/runforesight/received_events",
            "repos_url": "https://api.github.com/users/runforesight/repos",
            "site_admin": false,
            "starred_url": "https://api.github.com/users/runforesight/starred{/owner}{/repo}",
            "subscriptions_url": "https://api.github.com/users/runforesight/subscriptions",
            "type": "Organization",
            "url": "https://api.github.com/users/runforesight"
        }
    },
    "body": "Update package-lock.json",
    "changed_files": 2,
    "closed_at": "2022-01-21T13:00:18Z",
    "comment_data": [],
    "comment_regular_data": [],
    "comments": 0,
    "comments_url": "https://api.github.com/repos/runforesight/foresight-cli/issues/2/comments",
    "commit_data": [
        {
            "author": {
                "avatar_url": "https://avatars.githubusercontent.com/u/86224476?v=4",
                "events_url": "https://api.github.com/users/bcaglayan/events{/privacy}",
                "followers_url": "https://api.github.com/users/bcaglayan/followers",
                "following_url": "https://api.github.com/users/bcaglayan/following{/other_user}",
                "gists_url": "https://api.github.com/users/bcaglayan/gists{/gist_id}",
                "gravatar_id": "",
                "html_url": "https://github.com/bcaglayan",
                "id": 86224476,
                "login": "bcaglayan",
                "node_id": "MDQ6VXNlcjg2MjI0NDc2",
                "organizations_url": "https://api.github.com/users/bcaglayan/orgs",
                "received_events_url": "https://api.github.com/users/bcaglayan/received_events",
                "repos_url": "https://api.github.com/users/bcaglayan/repos",
                "site_admin": false,
                "starred_url": "https://api.github.com/users/bcaglayan/starred{/owner}{/repo}",
                "subscriptions_url": "https://api.github.com/users/bcaglayan/subscriptions",
                "type": "User",
                "url": "https://api.github.com/users/bcaglayan"
            },
            "comments_url": "https://api.github.com/repos/runforesight/foresight-cli/commits/0e112612b8f8d18aba7c609accbc277ac01b127b/comments",
            "commit": {
                "author": {
                    "date": "2022-01-21T12:59:24Z",
                    "email": "batuhan@thundra.io",
                    "name": "bcaglayan"
                },
                "comment_count": 0,
                "committer": {
                    "date": "2022-01-21T12:59:24Z",
                    "email": "batuhan@thundra.io",
                    "name": "bcaglayan"
                },
                "message": "Update package-lock.json",
                "tree": {
                    "sha": "b18233c86f5b9d8c93237fdd2b922e781b1b5b1a",
                    "url": "https://api.github.com/repos/runforesight/foresight-cli/git/trees/b18233c86f5b9d8c93237fdd2b922e781b1b5b1a"
                },
                "url": "https://api.github.com/repos/runforesight/foresight-cli/git/commits/0e112612b8f8d18aba7c609accbc277ac01b127b",
                "verification": {
                    "payload": null,
                    "reason": "unsigned",
                    "signature": null,
                    "verified": false
                }
            },
            "committer": {
                "avatar_url": "https://avatars.githubusercontent.com/u/86224476?v=4",
                "events_url": "https://api.github.com/users/bcaglayan/events{/privacy}",
                "followers_url": "https://api.github.com/users/bcaglayan/followers",
                "following_url": "https://api.github.com/users/bcaglayan/following{/other_user}",
                "gists_url": "https://api.github.com/users/bcaglayan/gists{/gist_id}",
                "gravatar_id": "",
                "html_url": "https://github.com/bcaglayan",
                "id": 86224476,
                "login": "bcaglayan",
                "node_id": "MDQ6VXNlcjg2MjI0NDc2",
                "organizations_url": "https://api.github.com/users/bcaglayan/orgs",
                "received_events_url": "https://api.github.com/users/bcaglayan/received_events",
                "repos_url": "https://api.github.com/users/bcaglayan/repos",
                "site_admin": false,
                "starred_url": "https://api.github.com/users/bcaglayan/starred{/owner}{/repo}",
                "subscriptions_url": "https://api.github.com/users/bcaglayan/subscriptions",
                "type": "User",
                "url": "https://api.github.com/users/bcaglayan"
            },
            "html_url": "https://github.com/runforesight/foresight-cli/commit/0e112612b8f8d18aba7c609accbc277ac01b127b",
            "node_id": "C_kwDOGkVhHdoAKDBlMTEyNjEyYjhmOGQxOGFiYTdjNjA5YWNjYmMyNzdhYzAxYjEyN2I",
            "parents": [
                {
                    "html_url": "https://github.com/runforesight/foresight-cli/commit/abf08c03b54a829c41ecf2b6f0e17e527e81f951",
                    "sha": "abf08c03b54a829c41ecf2b6f0e17e527e81f951",
                    "url": "https://api.github.com/repos/runforesight/foresight-cli/commits/abf08c03b54a829c41ecf2b6f0e17e527e81f951"
                }
            ],
            "sha": "0e112612b8f8d18aba7c609accbc277ac01b127b",
            "url": "https://api.github.com/repos/runforesight/foresight-cli/commits/0e112612b8f8d18aba7c609accbc277ac01b127b"
        }
    ],
    "commits": 1,
    "commits_url": "https://api.github.com/repos/runforesight/foresight-cli/pulls/2/commits",
    "created_at": "2022-01-21T12:59:42Z",
    "deletions": 164,
    "diff_url": "https://github.com/runforesight/foresight-cli/pull/2.diff",
    "draft": false,
    "head": {
        "label": "runforesight:update-packagelockjson",
        "ref": "update-packagelockjson",
        "repo": {
            "allow_forking": true,
            "archive_url": "https://api.github.com/repos/runforesight/foresight-cli/{archive_format}{/ref}",
            "archived": false,
            "assignees_url": "https://api.github.com/repos/runforesight/foresight-cli/assignees{/user}",
            "blobs_url": "https://api.github.com/repos/runforesight/foresight-cli/git/blobs{/sha}",
            "branches_url": "https://api.github.com/repos/runforesight/foresight-cli/branches{/branch}",
            "clone_url": "https://github.com/runforesight/foresight-cli.git",
            "collaborators_url": "https://api.github.com/repos/runforesight/foresight-cli/collaborators{/collaborator}",
            "comments_url": "https://api.github.com/repos/runforesight/foresight-cli/comments{/number}",
            "commits_url": "https://api.github.com/repos/runforesight/foresight-cli/commits{/sha}",
            "compare_url": "https://api.github.com/repos/runforesight/foresight-cli/compare/{base}...{head}",
            "contents_url": "https://api.github.com/repos/runforesight/foresight-cli/contents/{+path}",
            "contributors_url": "https://api.github.com/repos/runforesight/foresight-cli/contributors",
            "created_at": "2021-12-22T06:18:56Z",
            "default_branch": "master",
            "deployments_url": "https://api.github.com/repos/runforesight/foresight-cli/deployments",
            "description": "Foresight CLI",
            "disabled": false,
            "downloads_url": "https://api.github.com/repos/runforesight/foresight-cli/downloads",
            "events_url": "https://api.github.com/repos/runforesight/foresight-cli/events",
            "fork": false,
            "forks": 1,
            "forks_count": 1,
            "forks_url": "https://api.github.com/repos/runforesight/foresight-cli/forks",
            "full_name": "runforesight/foresight-cli",
            "git_commits_url": "https://api.github.com/repos/runforesight/foresight-cli/git/commits{/sha}",
            "git_refs_url": "https://api.github.com/repos/runforesight/foresight-cli/git/refs{/sha}",
            "git_tags_url": "https://api.github.com/repos/runforesight/foresight-cli/git/tags{/sha}",
            "git_url": "git://github.com/runforesight/foresight-cli.git",
            "has_discussions": false,
            "has_downloads": true,
            "has_issues": true,
            "has_pages": false,
            "has_projects": false,
            "has_wiki": true,
            "homepage": "",
            "hooks_url": "https://api.github.com/repos/runforesight/foresight-cli/hooks",
            "html_url": "https://github.com/runforesight/foresight-cli",
            "id": 440754461,
            "is_template": false,
            "issue_comment_url": "https://api.github.com/repos/runforesight/foresight-cli/issues/comments{/number}",
            "issue_events_url": "https://api.github.com/repos/runforesight/foresight-cli/issues/events{/number}",
            "issues_url": "https://api.github.com/repos/runforesight/foresight-cli/issues{/number}",
            "keys_url": "https://api.github.com/repos/runforesight/foresight-cli/keys{/key_id}",
            "labels_url": "https://api.github.com/repos/runforesight/foresight-cli/labels{/name}",
            "language": "TypeScript",
            "languages_url": "https://api.github.com/repos/runforesight/foresight-cli/languages",
            "license": {
                "key": "apache-2.0",
                "name": "Apache License 2.0",
                "node_id": "MDc6TGljZW5zZTI=",
                "spdx_id": "Apache-2.0",
                "url": "https://api.github.com/licenses/apache-2.0"
            },
            "merges_url": "https://api.github.com/repos/runforesight/foresight-cli/merges",
            "milestones_url": "https://api.github.com/repos/runforesight/foresight-cli/milestones{/number}",
            "mirror_url": null,
            "name": "foresight-cli",
            "node_id": "R_kgDOGkVhHQ",
            "notifications_url": "https://api.github.com/repos/runforesight/foresight-cli/notifications{?since,all,participating}",
            "open_issues": 1,
            "open_issues_count": 1,
            "owner": {
                "avatar_url": "https://avatars.githubusercontent.com/u/103429428?v=4",
                "events_url": "https://api.github.com/users/runforesight/events{/privacy}",
                "followers_url": "https://api.github.com/users/runforesight/followers",
                "following_url": "https://api.github.com/users/runforesight/following{/other_user}",
                "gists_url": "https://api.github.com/users/runforesight/gists{/gist_id}",
                "gravatar_id": "",
                "html_url": "https://github.com/runforesight",
                "id": 103429428,
                "login": "runforesight",
                "node_id": "O_kgDOBio1NA",
                "organizations_url": "https://api.github.com/users/runforesight/orgs",
                "received_events_url": "https://api.github.com/users/runforesight/received_events",
                "repos_url": "https://api.github.com/users/runforesight/repos",
                "site_admin": false,
                "starred_url": "https://api.github.com/users/runforesight/starred{/owner}{/repo}",
                "subscriptions_url": "https://api.github.com/users/runforesight/subscriptions",
                "type": "Organization",
                "url": "https://api.github.com/users/runforesight"
            },
            "private": false,
            "pulls_url": "https://api.github.com/repos/runforesight/foresight-cli/pulls{/number}",
            "pushed_at": "2023-02-20T12:51:45Z",
            "releases_url": "https://api.github.com/repos/runforesight/foresight-cli/releases{/id}",
            "size": 1069,
            "ssh_url": "git@github.com:runforesight/foresight-cli.git",
            "stargazers_count": 3,
            "stargazers_url": "https://api.github.com/repos/runforesight/foresight-cli/stargazers",
            "statuses_url": "https://api.github.com/repos/runforesight/foresight-cli/statuses/{sha}",
            "subscribers_url": "https://api.github.com/repos/runforesight/foresight-cli/subscribers",
            "subscription_url": "https://api.github.com/repos/runforesight/foresight-cli/subscription",
            "svn_url": "https://github.com/runforesight/foresight-cli",
            "tags_url": "https://api.github.com/repos/runforesight/foresight-cli/tags",
            "teams_url": "https://api.github.com/repos/runforesight/foresight-cli/teams",
            "topics": [],
            "trees_url": "https://api.github.com/repos/runforesight/foresight-cli/git/trees{/sha}",
            "updated_at": "2023-01-31T19:23:30Z",
            "url": "https://api.github.com/repos/runforesight/foresight-cli",
            "visibility": "public",
            "watchers": 3,
            "watchers_count": 3,
            "web_commit_signoff_required": false
        },
        "sha": "0e112612b8f8d18aba7c609accbc277ac01b127b",
        "user": {
            "avatar_url": "https://avatars.githubusercontent.com/u/103429428?v=4",
            "events_url": "https://api.github.com/users/runforesight/events{/privacy}",
            "followers_url": "https://api.github.com/users/runforesight/followers",
            "following_url": "https://api.github.com/users/runforesight/following{/other_user}",
            "gists_url": "https://api.github.com/users/runforesight/gists{/gist_id}",
            "gravatar_id": "",
            "html_url": "https://github.com/runforesight",
            "id": 103429428,
            "login": "runforesight",
            "node_id": "O_kgDOBio1NA",
            "organizations_url": "https://api.github.com/users/runforesight/orgs",
            "received_events_url": "https://api.github.com/users/runforesight/received_events",
            "repos_url": "https://api.github.com/users/runforesight/repos",
            "site_admin": false,
            "starred_url": "https://api.github.com/users/runforesight/starred{/owner}{/repo}",
            "subscriptions_url": "https://api.github.com/users/runforesight/subscriptions",
            "type": "Organization",
            "url": "https://api.github.com/users/runforesight"
        }
    },
    "html_url": "https://github.com/runforesight/foresight-cli/pull/2",
    "id": 828503375,
    "issue_url": "https://api.github.com/repos/runforesight/foresight-cli/issues/2",
    "labels": [],
    "locked": false,
    "maintainer_can_modify": false,
    "merge_commit_sha": "7445e4855bcc096d9b288f7189b760ee878ef331",
    "mergeable": null,
    "mergeable_state": "unknown",
    "merged": true,
    "merged_at": "2022-01-21T13:00:18Z",
    "merged_by": {
        "avatar_url": "https://avatars.githubusercontent.com/u/3482186?v=4",
        "events_url": "https://api.github.com/users/suleymanbarman/events{/privacy}",
        "followers_url": "https://api.github.com/users/suleymanbarman/followers",
        "following_url": "https://api.github.com/users/suleymanbarman/following{/other_user}",
        "gists_url": "https://api.github.com/users/suleymanbarman/gists{/gist_id}",
        "gravatar_id": "",
        "html_url": "https://github.com/suleymanbarman",
        "id": 3482186,
        "login": "suleymanbarman",
        "node_id": "MDQ6VXNlcjM0ODIxODY=",
        "organizations_url": "https://api.github.com/users/suleymanbarman/orgs",
        "received_events_url": "https://api.github.com/users/suleymanbarman/received_events",
        "repos_url": "https://api.github.com/users/suleymanbarman/repos",
        "site_admin": false,
        "starred_url": "https://api.github.com/users/suleymanbarman/starred{/owner}{/repo}",
        "subscriptions_url": "https://api.github.com/users/suleymanbarman/subscriptions",
        "type": "User",
        "url": "https://api.github.com/users/suleymanbarman"
    },
    "milestone": null,
    "node_id": "PR_kwDOGkVhHc4xYfVP",
    "number": 2,
    "patch_url": "https://github.com/runforesight/foresight-cli/pull/2.patch",
    "rebaseable": null,
    "requested_reviewers": [],
    "requested_teams": [],
    "review_comment_url": "https://api.github.com/repos/runforesight/foresight-cli/pulls/comments{/number}",
    "review_comments": 0,
    "review_comments_url": "https://api.github.com/repos/runforesight/foresight-cli/pulls/2/comments",
    "state": "closed",
    "statuses_url": "https://api.github.com/repos/runforesight/foresight-cli/statuses/0e112612b8f8d18aba7c609accbc277ac01b127b",
    "title": "Update package-lock.json",
    "updated_at": "2022-01-21T13:00:19Z",
    "url": "https://api.github.com/repos/runforesight/foresight-cli/pulls/2",
    "user": {
        "avatar_url": "https://avatars.githubusercontent.com/u/86224476?v=4",
        "events_url": "https://api.github.com/users/bcaglayan/events{/privacy}",
        "followers_url": "https://api.github.com/users/bcaglayan/followers",
        "following_url": "https://api.github.com/users/bcaglayan/following{/other_user}",
        "gists_url": "https://api.github.com/users/bcaglayan/gists{/gist_id}",
        "gravatar_id": "",
        "html_url": "https://github.com/bcaglayan",
        "id": 86224476,
        "login": "bcaglayan",
        "node_id": "MDQ6VXNlcjg2MjI0NDc2",
        "organizations_url": "https://api.github.com/users/bcaglayan/orgs",
        "received_events_url": "https://api.github.com/users/bcaglayan/received_events",
        "repos_url": "https://api.github.com/users/bcaglayan/repos",
        "site_admin": false,
        "starred_url": "https://api.github.com/users/bcaglayan/starred{/owner}{/repo}",
        "subscriptions_url": "https://api.github.com/users/bcaglayan/subscriptions",
        "type": "User",
        "url": "https://api.github.com/users/bcaglayan"
    }
}